<?xml version="1.0" ?>
<CommonRoadSolution benchmark_id="KS2:SM1:CHN_Sha-4_1_T-1:2018b" date="2019-12-15">
  <ksTrajectory planningProblem="2">
    <ksState>
      <x>-54.9653</x>
      <y>-1.8032</y>
      <orientation>0.0048</orientation>
      <velocity>2.0</velocity>
      <steeringAngle>0.0</steeringAngle>
      <time>0</time>
    </ksState>
    <ksState>
      <x>-54.765302303995576</x>
      <y>-1.8022400036863957</y>
      <orientation>0.0048</orientation>
      <velocity>2.0</velocity>
      <steeringAngle>0.0</steeringAngle>
      <time>1</time>
    </ksState>
    <ksState>
      <x>-54.56530460799115</x>
      <y>-1.8012800073727915</y>
      <orientation>0.0048</orientation>
      <velocity>2.0</velocity>
      <steeringAngle>0.0</steeringAngle>
      <time>2</time>
    </ksState>
    <ksState>
      <x>-54.36530691198673</x>
      <y>-1.8003200110591873</y>
      <orientation>0.0048</orientation>
      <velocity>2.0</velocity>
      <steeringAngle>0.0</steeringAngle>
      <time>3</time>
    </ksState>
    <ksState>
      <x>-54.165309215982305</x>
      <y>-1.7993600147455828</y>
      <orientation>0.0048</orientation>
      <velocity>2.0</velocity>
      <steeringAngle>0.0</steeringAngle>
      <time>4</time>
    </ksState>
    <ksState>
      <x>-53.96531151997788</x>
      <y>-1.7984000184319786</y>
      <orientation>0.0048</orientation>
      <velocity>2.0</velocity>
      <steeringAngle>0.0</steeringAngle>
      <time>5</time>
    </ksState>
    <ksState>
      <x>-53.76531382397346</x>
      <y>-1.7974400221183744</y>
      <orientation>0.0048</orientation>
      <velocity>2.0</velocity>
      <steeringAngle>0.0</steeringAngle>
      <time>6</time>
    </ksState>
    <ksState>
      <x>-53.565316127969034</x>
      <y>-1.7964800258047702</y>
      <orientation>0.0048</orientation>
      <velocity>2.0</velocity>
      <steeringAngle>0.0</steeringAngle>
      <time>7</time>
    </ksState>
    <ksState>
      <x>-53.36531843196461</x>
      <y>-1.795520029491166</y>
      <orientation>0.0048</orientation>
      <velocity>2.0</velocity>
      <steeringAngle>0.0</steeringAngle>
      <time>8</time>
    </ksState>
    <ksState>
      <x>-53.16532073596019</x>
      <y>-1.7945600331775615</y>
      <orientation>0.0048</orientation>
      <velocity>2.0</velocity>
      <steeringAngle>0.0</steeringAngle>
      <time>9</time>
    </ksState>
    <ksState>
      <x>-52.96532303995576</x>
      <y>-1.7936000368639573</y>
      <orientation>0.0048</orientation>
      <velocity>2.0</velocity>
      <steeringAngle>0.0</steeringAngle>
      <time>10</time>
    </ksState>
    <ksState>
      <x>-52.76532534395134</x>
      <y>-1.792640040550353</y>
      <orientation>0.0048</orientation>
      <velocity>2.0</velocity>
      <steeringAngle>0.0</steeringAngle>
      <time>11</time>
    </ksState>
    <ksState>
      <x>-52.565327647946916</x>
      <y>-1.7916800442367489</y>
      <orientation>0.0048</orientation>
      <velocity>2.0</velocity>
      <steeringAngle>0.0</steeringAngle>
      <time>12</time>
    </ksState>
    <ksState>
      <x>-52.36532995194249</x>
      <y>-1.7907200479231447</y>
      <orientation>0.0048</orientation>
      <velocity>2.0</velocity>
      <steeringAngle>0.0</steeringAngle>
      <time>13</time>
    </ksState>
    <ksState>
      <x>-52.16533225593807</x>
      <y>-1.7897600516095402</y>
      <orientation>0.0048</orientation>
      <velocity>2.0</velocity>
      <steeringAngle>0.0</steeringAngle>
      <time>14</time>
    </ksState>
    <ksState>
      <x>-51.965334559933645</x>
      <y>-1.788800055295936</y>
      <orientation>0.0048</orientation>
      <velocity>2.0</velocity>
      <steeringAngle>0.0</steeringAngle>
      <time>15</time>
    </ksState>
    <ksState>
      <x>-51.76533686392922</x>
      <y>-1.7878400589823318</y>
      <orientation>0.0048</orientation>
      <velocity>2.0</velocity>
      <steeringAngle>0.0</steeringAngle>
      <time>16</time>
    </ksState>
    <ksState>
      <x>-51.5653391679248</x>
      <y>-1.7868800626687276</y>
      <orientation>0.0048</orientation>
      <velocity>2.0</velocity>
      <steeringAngle>0.0</steeringAngle>
      <time>17</time>
    </ksState>
    <ksState>
      <x>-51.365341471920374</x>
      <y>-1.7859200663551233</y>
      <orientation>0.0048</orientation>
      <velocity>2.0</velocity>
      <steeringAngle>0.0</steeringAngle>
      <time>18</time>
    </ksState>
    <ksState>
      <x>-51.16534377591595</x>
      <y>-1.784960070041519</y>
      <orientation>0.0048</orientation>
      <velocity>2.0</velocity>
      <steeringAngle>0.0</steeringAngle>
      <time>19</time>
    </ksState>
    <ksState>
      <x>-50.96534607991153</x>
      <y>-1.7840000737279147</y>
      <orientation>0.0048</orientation>
      <velocity>2.0</velocity>
      <steeringAngle>0.0</steeringAngle>
      <time>20</time>
    </ksState>
    <ksState>
      <x>-50.7653483839071</x>
      <y>-1.7830400774143105</y>
      <orientation>0.0048</orientation>
      <velocity>2.0</velocity>
      <steeringAngle>0.0</steeringAngle>
      <time>21</time>
    </ksState>
    <ksState>
      <x>-50.56535068790268</x>
      <y>-1.7820800811007063</y>
      <orientation>0.0048</orientation>
      <velocity>2.0</velocity>
      <steeringAngle>0.0</steeringAngle>
      <time>22</time>
    </ksState>
    <ksState>
      <x>-50.365352991898256</x>
      <y>-1.781120084787102</y>
      <orientation>0.0048</orientation>
      <velocity>2.0</velocity>
      <steeringAngle>0.0</steeringAngle>
      <time>23</time>
    </ksState>
    <ksState>
      <x>-50.16535529589383</x>
      <y>-1.7801600884734976</y>
      <orientation>0.0048</orientation>
      <velocity>2.0</velocity>
      <steeringAngle>0.0</steeringAngle>
      <time>24</time>
    </ksState>
    <ksState>
      <x>-49.96535759988941</x>
      <y>-1.7792000921598934</y>
      <orientation>0.0048</orientation>
      <velocity>2.0</velocity>
      <steeringAngle>0.0</steeringAngle>
      <time>25</time>
    </ksState>
    <ksState>
      <x>-49.765359903884985</x>
      <y>-1.7782400958462892</y>
      <orientation>0.0048</orientation>
      <velocity>2.0</velocity>
      <steeringAngle>0.0</steeringAngle>
      <time>26</time>
    </ksState>
    <ksState>
      <x>-49.56536220788056</x>
      <y>-1.777280099532685</y>
      <orientation>0.0048</orientation>
      <velocity>2.0</velocity>
      <steeringAngle>0.0</steeringAngle>
      <time>27</time>
    </ksState>
    <ksState>
      <x>-49.36536451187614</x>
      <y>-1.7763201032190807</y>
      <orientation>0.0048</orientation>
      <velocity>2.0</velocity>
      <steeringAngle>0.0</steeringAngle>
      <time>28</time>
    </ksState>
    <ksState>
      <x>-49.165366815871714</x>
      <y>-1.7753601069054763</y>
      <orientation>0.0048</orientation>
      <velocity>2.0</velocity>
      <steeringAngle>0.0</steeringAngle>
      <time>29</time>
    </ksState>
    <ksState>
      <x>-48.96536911986729</x>
      <y>-1.774400110591872</y>
      <orientation>0.0048</orientation>
      <velocity>2.0</velocity>
      <steeringAngle>0.0</steeringAngle>
      <time>30</time>
    </ksState>
    <ksState>
      <x>-48.76537142386287</x>
      <y>-1.7734401142782679</y>
      <orientation>0.0048</orientation>
      <velocity>2.0</velocity>
      <steeringAngle>0.0</steeringAngle>
      <time>31</time>
    </ksState>
    <ksState>
      <x>-48.56537372785844</x>
      <y>-1.7724801179646636</y>
      <orientation>0.0048</orientation>
      <velocity>2.0</velocity>
      <steeringAngle>0.0</steeringAngle>
      <time>32</time>
    </ksState>
    <ksState>
      <x>-48.36537603185402</x>
      <y>-1.7715201216510594</y>
      <orientation>0.0048</orientation>
      <velocity>2.0</velocity>
      <steeringAngle>0.0</steeringAngle>
      <time>33</time>
    </ksState>
    <ksState>
      <x>-48.165378335849596</x>
      <y>-1.770560125337455</y>
      <orientation>0.0048</orientation>
      <velocity>2.0</velocity>
      <steeringAngle>0.0</steeringAngle>
      <time>34</time>
    </ksState>
    <ksState>
      <x>-47.96538063984517</x>
      <y>-1.7696001290238508</y>
      <orientation>0.0048</orientation>
      <velocity>2.0</velocity>
      <steeringAngle>0.0</steeringAngle>
      <time>35</time>
    </ksState>
    <ksState>
      <x>-47.76538294384075</x>
      <y>-1.7686401327102466</y>
      <orientation>0.0048</orientation>
      <velocity>2.0</velocity>
      <steeringAngle>0.0</steeringAngle>
      <time>36</time>
    </ksState>
    <ksState>
      <x>-47.565385247836325</x>
      <y>-1.7676801363966423</y>
      <orientation>0.0048</orientation>
      <velocity>2.0</velocity>
      <steeringAngle>0.0</steeringAngle>
      <time>37</time>
    </ksState>
    <ksState>
      <x>-47.3653875518319</x>
      <y>-1.7667201400830381</y>
      <orientation>0.0048</orientation>
      <velocity>2.0</velocity>
      <steeringAngle>0.0</steeringAngle>
      <time>38</time>
    </ksState>
    <ksState>
      <x>-47.16538985582748</x>
      <y>-1.7657601437694337</y>
      <orientation>0.0048</orientation>
      <velocity>2.0</velocity>
      <steeringAngle>0.0</steeringAngle>
      <time>39</time>
    </ksState>
    <ksState>
      <x>-46.965392159823054</x>
      <y>-1.7648001474558295</y>
      <orientation>0.0048</orientation>
      <velocity>2.0</velocity>
      <steeringAngle>0.0</steeringAngle>
      <time>40</time>
    </ksState>
    <ksState>
      <x>-46.76539446381863</x>
      <y>-1.7638401511422253</y>
      <orientation>0.0048</orientation>
      <velocity>2.0</velocity>
      <steeringAngle>0.0</steeringAngle>
      <time>41</time>
    </ksState>
    <ksState>
      <x>-46.56539676781421</x>
      <y>-1.762880154828621</y>
      <orientation>0.0048</orientation>
      <velocity>2.0</velocity>
      <steeringAngle>0.0</steeringAngle>
      <time>42</time>
    </ksState>
    <ksState>
      <x>-46.36539907180978</x>
      <y>-1.7619201585150168</y>
      <orientation>0.0048</orientation>
      <velocity>2.0</velocity>
      <steeringAngle>0.0</steeringAngle>
      <time>43</time>
    </ksState>
    <ksState>
      <x>-46.16540137580536</x>
      <y>-1.7609601622014124</y>
      <orientation>0.0048</orientation>
      <velocity>2.0</velocity>
      <steeringAngle>0.0</steeringAngle>
      <time>44</time>
    </ksState>
    <ksState>
      <x>-45.965403679800936</x>
      <y>-1.7600001658878082</y>
      <orientation>0.0048</orientation>
      <velocity>2.0</velocity>
      <steeringAngle>0.0</steeringAngle>
      <time>45</time>
    </ksState>
    <ksState>
      <x>-45.76540598379651</x>
      <y>-1.759040169574204</y>
      <orientation>0.0048</orientation>
      <velocity>2.0</velocity>
      <steeringAngle>0.0</steeringAngle>
      <time>46</time>
    </ksState>
    <ksState>
      <x>-45.56540828779209</x>
      <y>-1.7580801732605997</y>
      <orientation>0.0048</orientation>
      <velocity>2.0</velocity>
      <steeringAngle>0.0</steeringAngle>
      <time>47</time>
    </ksState>
    <ksState>
      <x>-45.365410591787665</x>
      <y>-1.7571201769469955</y>
      <orientation>0.0048</orientation>
      <velocity>2.0</velocity>
      <steeringAngle>0.0</steeringAngle>
      <time>48</time>
    </ksState>
    <ksState>
      <x>-45.16541289578324</x>
      <y>-1.756160180633391</y>
      <orientation>0.0048</orientation>
      <velocity>2.0</velocity>
      <steeringAngle>0.0</steeringAngle>
      <time>49</time>
    </ksState>
    <ksState>
      <x>-44.96541519977882</x>
      <y>-1.7552001843197869</y>
      <orientation>0.0048</orientation>
      <velocity>2.0</velocity>
      <steeringAngle>0.0</steeringAngle>
      <time>50</time>
    </ksState>
    <ksState>
      <x>-44.765417503774394</x>
      <y>-1.7542401880061826</y>
      <orientation>0.0048</orientation>
      <velocity>2.0</velocity>
      <steeringAngle>0.0</steeringAngle>
      <time>51</time>
    </ksState>
    <ksState>
      <x>-44.56541980776997</x>
      <y>-1.7532801916925784</y>
      <orientation>0.0048</orientation>
      <velocity>2.0</velocity>
      <steeringAngle>0.0</steeringAngle>
      <time>52</time>
    </ksState>
    <ksState>
      <x>-44.36542211176555</x>
      <y>-1.7523201953789742</y>
      <orientation>0.0048</orientation>
      <velocity>2.0</velocity>
      <steeringAngle>0.0</steeringAngle>
      <time>53</time>
    </ksState>
    <ksState>
      <x>-44.16542441576112</x>
      <y>-1.7513601990653698</y>
      <orientation>0.0048</orientation>
      <velocity>2.0</velocity>
      <steeringAngle>0.0</steeringAngle>
      <time>54</time>
    </ksState>
    <ksState>
      <x>-43.9654267197567</x>
      <y>-1.7504002027517656</y>
      <orientation>0.0048</orientation>
      <velocity>2.0</velocity>
      <steeringAngle>0.0</steeringAngle>
      <time>55</time>
    </ksState>
    <ksState>
      <x>-43.765429023752276</x>
      <y>-1.7494402064381613</y>
      <orientation>0.0048</orientation>
      <velocity>2.0</velocity>
      <steeringAngle>0.0</steeringAngle>
      <time>56</time>
    </ksState>
    <ksState>
      <x>-43.56543132774785</x>
      <y>-1.7484802101245571</y>
      <orientation>0.0048</orientation>
      <velocity>2.0</velocity>
      <steeringAngle>0.0</steeringAngle>
      <time>57</time>
    </ksState>
    <ksState>
      <x>-43.36543363174343</x>
      <y>-1.747520213810953</y>
      <orientation>0.0048</orientation>
      <velocity>2.0</velocity>
      <steeringAngle>0.0</steeringAngle>
      <time>58</time>
    </ksState>
    <ksState>
      <x>-43.165435935739005</x>
      <y>-1.7465602174973485</y>
      <orientation>0.0048</orientation>
      <velocity>2.0</velocity>
      <steeringAngle>0.0</steeringAngle>
      <time>59</time>
    </ksState>
    <ksState>
      <x>-42.96543823973458</x>
      <y>-1.7456002211837442</y>
      <orientation>0.0048</orientation>
      <velocity>2.0</velocity>
      <steeringAngle>0.0</steeringAngle>
      <time>60</time>
    </ksState>
    <ksState>
      <x>-42.76544054373016</x>
      <y>-1.74464022487014</y>
      <orientation>0.0048</orientation>
      <velocity>2.0</velocity>
      <steeringAngle>0.0</steeringAngle>
      <time>61</time>
    </ksState>
    <ksState>
      <x>-42.565442847725734</x>
      <y>-1.7436802285565358</y>
      <orientation>0.0048</orientation>
      <velocity>2.0</velocity>
      <steeringAngle>0.0</steeringAngle>
      <time>62</time>
    </ksState>
    <ksState>
      <x>-42.36544515172131</x>
      <y>-1.7427202322429316</y>
      <orientation>0.0048</orientation>
      <velocity>2.0</velocity>
      <steeringAngle>0.0</steeringAngle>
      <time>63</time>
    </ksState>
    <ksState>
      <x>-42.16544745571689</x>
      <y>-1.7417602359293272</y>
      <orientation>0.0048</orientation>
      <velocity>2.0</velocity>
      <steeringAngle>0.0</steeringAngle>
      <time>64</time>
    </ksState>
    <ksState>
      <x>-41.96544975971246</x>
      <y>-1.740800239615723</y>
      <orientation>0.0048</orientation>
      <velocity>2.0</velocity>
      <steeringAngle>0.0</steeringAngle>
      <time>65</time>
    </ksState>
    <ksState>
      <x>-41.76545206370804</x>
      <y>-1.7398402433021187</y>
      <orientation>0.0048</orientation>
      <velocity>2.0</velocity>
      <steeringAngle>0.0</steeringAngle>
      <time>66</time>
    </ksState>
    <ksState>
      <x>-41.565454367703616</x>
      <y>-1.7388802469885145</y>
      <orientation>0.0048</orientation>
      <velocity>2.0</velocity>
      <steeringAngle>0.0</steeringAngle>
      <time>67</time>
    </ksState>
    <ksState>
      <x>-41.36545667169919</x>
      <y>-1.7379202506749103</y>
      <orientation>0.0048</orientation>
      <velocity>2.0</velocity>
      <steeringAngle>0.0</steeringAngle>
      <time>68</time>
    </ksState>
    <ksState>
      <x>-41.16545897569477</x>
      <y>-1.7369602543613059</y>
      <orientation>0.0048</orientation>
      <velocity>2.0</velocity>
      <steeringAngle>0.0</steeringAngle>
      <time>69</time>
    </ksState>
    <ksState>
      <x>-40.965461279690345</x>
      <y>-1.7360002580477016</y>
      <orientation>0.0048</orientation>
      <velocity>2.0</velocity>
      <steeringAngle>0.0</steeringAngle>
      <time>70</time>
    </ksState>
    <ksState>
      <x>-40.76546358368592</x>
      <y>-1.7350402617340974</y>
      <orientation>0.0048</orientation>
      <velocity>2.0</velocity>
      <steeringAngle>0.0</steeringAngle>
      <time>71</time>
    </ksState>
    <ksState>
      <x>-40.5654658876815</x>
      <y>-1.7340802654204932</y>
      <orientation>0.0048</orientation>
      <velocity>2.0</velocity>
      <steeringAngle>0.0</steeringAngle>
      <time>72</time>
    </ksState>
    <ksState>
      <x>-40.365468191677074</x>
      <y>-1.733120269106889</y>
      <orientation>0.0048</orientation>
      <velocity>2.0</velocity>
      <steeringAngle>0.0</steeringAngle>
      <time>73</time>
    </ksState>
    <ksState>
      <x>-40.16547049567265</x>
      <y>-1.7321602727932846</y>
      <orientation>0.0048</orientation>
      <velocity>2.0</velocity>
      <steeringAngle>0.0</steeringAngle>
      <time>74</time>
    </ksState>
    <ksState>
      <x>-39.96547279966823</x>
      <y>-1.7312002764796803</y>
      <orientation>0.0048</orientation>
      <velocity>2.0</velocity>
      <steeringAngle>0.0</steeringAngle>
      <time>75</time>
    </ksState>
    <ksState>
      <x>-39.7654751036638</x>
      <y>-1.7302402801660761</y>
      <orientation>0.0048</orientation>
      <velocity>2.0</velocity>
      <steeringAngle>0.0</steeringAngle>
      <time>76</time>
    </ksState>
    <ksState>
      <x>-39.56547740765938</x>
      <y>-1.729280283852472</y>
      <orientation>0.0048</orientation>
      <velocity>2.0</velocity>
      <steeringAngle>0.0</steeringAngle>
      <time>77</time>
    </ksState>
    <ksState>
      <x>-39.365479711654956</x>
      <y>-1.7283202875388677</y>
      <orientation>0.0048</orientation>
      <velocity>2.0</velocity>
      <steeringAngle>0.0</steeringAngle>
      <time>78</time>
    </ksState>
    <ksState>
      <x>-39.16548201565053</x>
      <y>-1.7273602912252632</y>
      <orientation>0.0048</orientation>
      <velocity>2.0</velocity>
      <steeringAngle>0.0</steeringAngle>
      <time>79</time>
    </ksState>
    <ksState>
      <x>-38.96548431964611</x>
      <y>-1.726400294911659</y>
      <orientation>0.0048</orientation>
      <velocity>2.0</velocity>
      <steeringAngle>0.0</steeringAngle>
      <time>80</time>
    </ksState>
    <ksState>
      <x>-38.765486623641685</x>
      <y>-1.7254402985980548</y>
      <orientation>0.0048</orientation>
      <velocity>2.0</velocity>
      <steeringAngle>0.0</steeringAngle>
      <time>81</time>
    </ksState>
    <ksState>
      <x>-38.56548892763726</x>
      <y>-1.7244803022844506</y>
      <orientation>0.0048</orientation>
      <velocity>2.0</velocity>
      <steeringAngle>0.0</steeringAngle>
      <time>82</time>
    </ksState>
    <ksState>
      <x>-38.36549123163284</x>
      <y>-1.7235203059708464</y>
      <orientation>0.0048</orientation>
      <velocity>2.0</velocity>
      <steeringAngle>0.0</steeringAngle>
      <time>83</time>
    </ksState>
    <ksState>
      <x>-38.165493535628414</x>
      <y>-1.722560309657242</y>
      <orientation>0.0048</orientation>
      <velocity>2.0</velocity>
      <steeringAngle>0.0</steeringAngle>
      <time>84</time>
    </ksState>
    <ksState>
      <x>-37.96549583962399</x>
      <y>-1.7216003133436377</y>
      <orientation>0.0048</orientation>
      <velocity>2.0</velocity>
      <steeringAngle>0.0</steeringAngle>
      <time>85</time>
    </ksState>
    <ksState>
      <x>-37.76549814361957</x>
      <y>-1.7206403170300335</y>
      <orientation>0.0048</orientation>
      <velocity>2.0</velocity>
      <steeringAngle>0.0</steeringAngle>
      <time>86</time>
    </ksState>
    <ksState>
      <x>-37.56550044761514</x>
      <y>-1.7196803207164293</y>
      <orientation>0.0048</orientation>
      <velocity>2.0</velocity>
      <steeringAngle>0.0</steeringAngle>
      <time>87</time>
    </ksState>
    <ksState>
      <x>-37.36550275161072</x>
      <y>-1.718720324402825</y>
      <orientation>0.0048</orientation>
      <velocity>2.0</velocity>
      <steeringAngle>0.0</steeringAngle>
      <time>88</time>
    </ksState>
    <ksState>
      <x>-37.165505055606296</x>
      <y>-1.7177603280892206</y>
      <orientation>0.0048</orientation>
      <velocity>2.0</velocity>
      <steeringAngle>0.0</steeringAngle>
      <time>89</time>
    </ksState>
    <ksState>
      <x>-36.96550735960187</x>
      <y>-1.7168003317756164</y>
      <orientation>0.0048</orientation>
      <velocity>2.0</velocity>
      <steeringAngle>0.0</steeringAngle>
      <time>90</time>
    </ksState>
    <ksState>
      <x>-36.76550966359745</x>
      <y>-1.7158403354620122</y>
      <orientation>0.0048</orientation>
      <velocity>2.0</velocity>
      <steeringAngle>0.0</steeringAngle>
      <time>91</time>
    </ksState>
    <ksState>
      <x>-36.565511967593025</x>
      <y>-1.714880339148408</y>
      <orientation>0.0048</orientation>
      <velocity>2.0</velocity>
      <steeringAngle>0.0</steeringAngle>
      <time>92</time>
    </ksState>
    <ksState>
      <x>-36.3655142715886</x>
      <y>-1.7139203428348038</y>
      <orientation>0.0048</orientation>
      <velocity>2.0</velocity>
      <steeringAngle>0.0</steeringAngle>
      <time>93</time>
    </ksState>
    <ksState>
      <x>-36.16551657558418</x>
      <y>-1.7129603465211993</y>
      <orientation>0.0048</orientation>
      <velocity>2.0</velocity>
      <steeringAngle>0.0</steeringAngle>
      <time>94</time>
    </ksState>
    <ksState>
      <x>-35.965518879579754</x>
      <y>-1.7120003502075951</y>
      <orientation>0.0048</orientation>
      <velocity>2.0</velocity>
      <steeringAngle>0.0</steeringAngle>
      <time>95</time>
    </ksState>
    <ksState>
      <x>-35.76552118357533</x>
      <y>-1.711040353893991</y>
      <orientation>0.0048</orientation>
      <velocity>2.0</velocity>
      <steeringAngle>0.0</steeringAngle>
      <time>96</time>
    </ksState>
    <ksState>
      <x>-35.56552348757091</x>
      <y>-1.7100803575803867</y>
      <orientation>0.0048</orientation>
      <velocity>2.0</velocity>
      <steeringAngle>0.0</steeringAngle>
      <time>97</time>
    </ksState>
    <ksState>
      <x>-35.36552579156648</x>
      <y>-1.7091203612667825</y>
      <orientation>0.0048</orientation>
      <velocity>2.0</velocity>
      <steeringAngle>0.0</steeringAngle>
      <time>98</time>
    </ksState>
    <ksState>
      <x>-35.16552809556206</x>
      <y>-1.708160364953178</y>
      <orientation>0.0048</orientation>
      <velocity>2.0</velocity>
      <steeringAngle>0.0</steeringAngle>
      <time>99</time>
    </ksState>
    <ksState>
      <x>-34.965530399557636</x>
      <y>-1.7072003686395738</y>
      <orientation>0.0048</orientation>
      <velocity>2.0</velocity>
      <steeringAngle>0.0</steeringAngle>
      <time>100</time>
    </ksState>
    <ksState>
      <x>-34.76553270355321</x>
      <y>-1.7062403723259696</y>
      <orientation>0.0048</orientation>
      <velocity>2.0</velocity>
      <steeringAngle>0.0</steeringAngle>
      <time>101</time>
    </ksState>
    <ksState>
      <x>-34.56553500754879</x>
      <y>-1.7052803760123654</y>
      <orientation>0.0048</orientation>
      <velocity>2.0</velocity>
      <steeringAngle>0.0</steeringAngle>
      <time>102</time>
    </ksState>
    <ksState>
      <x>-34.365537311544365</x>
      <y>-1.7043203796987612</y>
      <orientation>0.0048</orientation>
      <velocity>2.0</velocity>
      <steeringAngle>0.0</steeringAngle>
      <time>103</time>
    </ksState>
    <ksState>
      <x>-34.16553961553994</x>
      <y>-1.7033603833851567</y>
      <orientation>0.0048</orientation>
      <velocity>2.0</velocity>
      <steeringAngle>0.0</steeringAngle>
      <time>104</time>
    </ksState>
    <ksState>
      <x>-33.96554191953552</x>
      <y>-1.7024003870715525</y>
      <orientation>0.0048</orientation>
      <velocity>2.0</velocity>
      <steeringAngle>0.0</steeringAngle>
      <time>105</time>
    </ksState>
    <ksState>
      <x>-33.765544223531094</x>
      <y>-1.7014403907579483</y>
      <orientation>0.0048</orientation>
      <velocity>2.0</velocity>
      <steeringAngle>0.0</steeringAngle>
      <time>106</time>
    </ksState>
    <ksState>
      <x>-33.56554652752667</x>
      <y>-1.700480394444344</y>
      <orientation>0.0048</orientation>
      <velocity>2.0</velocity>
      <steeringAngle>0.0</steeringAngle>
      <time>107</time>
    </ksState>
    <ksState>
      <x>-33.36554883152225</x>
      <y>-1.6995203981307399</y>
      <orientation>0.0048</orientation>
      <velocity>2.0</velocity>
      <steeringAngle>0.0</steeringAngle>
      <time>108</time>
    </ksState>
    <ksState>
      <x>-33.16555113551782</x>
      <y>-1.6985604018171354</y>
      <orientation>0.0048</orientation>
      <velocity>2.0</velocity>
      <steeringAngle>0.0</steeringAngle>
      <time>109</time>
    </ksState>
    <ksState>
      <x>-32.9655534395134</x>
      <y>-1.6976004055035312</y>
      <orientation>0.0048</orientation>
      <velocity>2.0</velocity>
      <steeringAngle>0.0</steeringAngle>
      <time>110</time>
    </ksState>
    <ksState>
      <x>-32.765555743508976</x>
      <y>-1.696640409189927</y>
      <orientation>0.0048</orientation>
      <velocity>2.0</velocity>
      <steeringAngle>0.0</steeringAngle>
      <time>111</time>
    </ksState>
    <ksState>
      <x>-32.56555804750455</x>
      <y>-1.6956804128763228</y>
      <orientation>0.0048</orientation>
      <velocity>2.0</velocity>
      <steeringAngle>0.0</steeringAngle>
      <time>112</time>
    </ksState>
    <ksState>
      <x>-32.36556035150013</x>
      <y>-1.6947204165627185</y>
      <orientation>0.0048</orientation>
      <velocity>2.0</velocity>
      <steeringAngle>0.0</steeringAngle>
      <time>113</time>
    </ksState>
    <ksState>
      <x>-32.165562655495705</x>
      <y>-1.693760420249114</y>
      <orientation>0.0048</orientation>
      <velocity>2.0</velocity>
      <steeringAngle>0.0</steeringAngle>
      <time>114</time>
    </ksState>
    <ksState>
      <x>-31.96556495949128</x>
      <y>-1.69280042393551</y>
      <orientation>0.0048</orientation>
      <velocity>2.0</velocity>
      <steeringAngle>0.0</steeringAngle>
      <time>115</time>
    </ksState>
    <ksState>
      <x>-31.765567263486858</x>
      <y>-1.6918404276219057</y>
      <orientation>0.0048</orientation>
      <velocity>2.0</velocity>
      <steeringAngle>0.0</steeringAngle>
      <time>116</time>
    </ksState>
    <ksState>
      <x>-31.565569567482434</x>
      <y>-1.6908804313083015</y>
      <orientation>0.0048</orientation>
      <velocity>2.0</velocity>
      <steeringAngle>0.0</steeringAngle>
      <time>117</time>
    </ksState>
    <ksState>
      <x>-31.36557187147801</x>
      <y>-1.6899204349946972</y>
      <orientation>0.0048</orientation>
      <velocity>2.0</velocity>
      <steeringAngle>0.0</steeringAngle>
      <time>118</time>
    </ksState>
    <ksState>
      <x>-31.165574175473587</x>
      <y>-1.6889604386810928</y>
      <orientation>0.0048</orientation>
      <velocity>2.0</velocity>
      <steeringAngle>0.0</steeringAngle>
      <time>119</time>
    </ksState>
    <ksState>
      <x>-30.965576479469163</x>
      <y>-1.6880004423674886</y>
      <orientation>0.0048</orientation>
      <velocity>2.0</velocity>
      <steeringAngle>0.0</steeringAngle>
      <time>120</time>
    </ksState>
    <ksState>
      <x>-30.76557878346474</x>
      <y>-1.6870404460538844</y>
      <orientation>0.0048</orientation>
      <velocity>2.0</velocity>
      <steeringAngle>0.0</steeringAngle>
      <time>121</time>
    </ksState>
    <ksState>
      <x>-30.565581087460316</x>
      <y>-1.6860804497402802</y>
      <orientation>0.0048</orientation>
      <velocity>2.0</velocity>
      <steeringAngle>0.0</steeringAngle>
      <time>122</time>
    </ksState>
    <ksState>
      <x>-30.365583391455893</x>
      <y>-1.685120453426676</y>
      <orientation>0.0048</orientation>
      <velocity>2.0</velocity>
      <steeringAngle>0.0</steeringAngle>
      <time>123</time>
    </ksState>
    <ksState>
      <x>-30.16558569545147</x>
      <y>-1.6841604571130715</y>
      <orientation>0.0048</orientation>
      <velocity>2.0</velocity>
      <steeringAngle>0.0</steeringAngle>
      <time>124</time>
    </ksState>
    <ksState>
      <x>-29.965587999447045</x>
      <y>-1.6832004607994673</y>
      <orientation>0.0048</orientation>
      <velocity>2.0</velocity>
      <steeringAngle>0.0</steeringAngle>
      <time>125</time>
    </ksState>
    <ksState>
      <x>-29.76559030344262</x>
      <y>-1.682240464485863</y>
      <orientation>0.0048</orientation>
      <velocity>2.0</velocity>
      <steeringAngle>0.0</steeringAngle>
      <time>126</time>
    </ksState>
    <ksState>
      <x>-29.565592607438198</x>
      <y>-1.6812804681722588</y>
      <orientation>0.0048</orientation>
      <velocity>2.0</velocity>
      <steeringAngle>0.0</steeringAngle>
      <time>127</time>
    </ksState>
    <ksState>
      <x>-29.365594911433774</x>
      <y>-1.6803204718586546</y>
      <orientation>0.0048</orientation>
      <velocity>2.0</velocity>
      <steeringAngle>0.0</steeringAngle>
      <time>128</time>
    </ksState>
    <ksState>
      <x>-29.16559721542935</x>
      <y>-1.6793604755450502</y>
      <orientation>0.0048</orientation>
      <velocity>2.0</velocity>
      <steeringAngle>0.0</steeringAngle>
      <time>129</time>
    </ksState>
    <ksState>
      <x>-28.965599519424927</x>
      <y>-1.678400479231446</y>
      <orientation>0.0048</orientation>
      <velocity>2.0</velocity>
      <steeringAngle>0.0</steeringAngle>
      <time>130</time>
    </ksState>
    <ksState>
      <x>-28.765601823420504</x>
      <y>-1.6774404829178418</y>
      <orientation>0.0048</orientation>
      <velocity>2.0</velocity>
      <steeringAngle>0.0</steeringAngle>
      <time>131</time>
    </ksState>
    <ksState>
      <x>-28.56560412741608</x>
      <y>-1.6764804866042375</y>
      <orientation>0.0048</orientation>
      <velocity>2.0</velocity>
      <steeringAngle>0.0</steeringAngle>
      <time>132</time>
    </ksState>
    <ksState>
      <x>-28.365606431411656</x>
      <y>-1.6755204902906333</y>
      <orientation>0.0048</orientation>
      <velocity>2.0</velocity>
      <steeringAngle>0.0</steeringAngle>
      <time>133</time>
    </ksState>
    <ksState>
      <x>-28.165608735407233</x>
      <y>-1.6745604939770289</y>
      <orientation>0.0048</orientation>
      <velocity>2.0</velocity>
      <steeringAngle>0.0</steeringAngle>
      <time>134</time>
    </ksState>
    <ksState>
      <x>-27.96561103940281</x>
      <y>-1.6736004976634247</y>
      <orientation>0.0048</orientation>
      <velocity>2.0</velocity>
      <steeringAngle>0.0</steeringAngle>
      <time>135</time>
    </ksState>
    <ksState>
      <x>-27.765613343398385</x>
      <y>-1.6726405013498205</y>
      <orientation>0.0048</orientation>
      <velocity>2.0</velocity>
      <steeringAngle>0.0</steeringAngle>
      <time>136</time>
    </ksState>
    <ksState>
      <x>-27.56561564739396</x>
      <y>-1.6716805050362162</y>
      <orientation>0.0048</orientation>
      <velocity>2.0</velocity>
      <steeringAngle>0.0</steeringAngle>
      <time>137</time>
    </ksState>
    <ksState>
      <x>-27.365617951389538</x>
      <y>-1.670720508722612</y>
      <orientation>0.0048</orientation>
      <velocity>2.0</velocity>
      <steeringAngle>0.0</steeringAngle>
      <time>138</time>
    </ksState>
    <ksState>
      <x>-27.165620255385114</x>
      <y>-1.6697605124090076</y>
      <orientation>0.0048</orientation>
      <velocity>2.0</velocity>
      <steeringAngle>0.0</steeringAngle>
      <time>139</time>
    </ksState>
    <ksState>
      <x>-26.96562255938069</x>
      <y>-1.6688005160954034</y>
      <orientation>0.0048</orientation>
      <velocity>2.0</velocity>
      <steeringAngle>0.0</steeringAngle>
      <time>140</time>
    </ksState>
    <ksState>
      <x>-26.765624863376267</x>
      <y>-1.6678405197817991</y>
      <orientation>0.0048</orientation>
      <velocity>2.0</velocity>
      <steeringAngle>0.0</steeringAngle>
      <time>141</time>
    </ksState>
    <ksState>
      <x>-26.565627167371844</x>
      <y>-1.666880523468195</y>
      <orientation>0.0048</orientation>
      <velocity>2.0</velocity>
      <steeringAngle>0.0</steeringAngle>
      <time>142</time>
    </ksState>
    <ksState>
      <x>-26.36562947136742</x>
      <y>-1.6659205271545907</y>
      <orientation>0.0048</orientation>
      <velocity>2.0</velocity>
      <steeringAngle>0.0</steeringAngle>
      <time>143</time>
    </ksState>
    <ksState>
      <x>-26.165631775362996</x>
      <y>-1.6649605308409863</y>
      <orientation>0.0048</orientation>
      <velocity>2.0</velocity>
      <steeringAngle>0.0</steeringAngle>
      <time>144</time>
    </ksState>
    <ksState>
      <x>-25.965634079358573</x>
      <y>-1.664000534527382</y>
      <orientation>0.0048</orientation>
      <velocity>2.0</velocity>
      <steeringAngle>0.0</steeringAngle>
      <time>145</time>
    </ksState>
    <ksState>
      <x>-25.76563638335415</x>
      <y>-1.6630405382137778</y>
      <orientation>0.0048</orientation>
      <velocity>2.0</velocity>
      <steeringAngle>0.0</steeringAngle>
      <time>146</time>
    </ksState>
    <ksState>
      <x>-25.565638687349725</x>
      <y>-1.6620805419001736</y>
      <orientation>0.0048</orientation>
      <velocity>2.0</velocity>
      <steeringAngle>0.0</steeringAngle>
      <time>147</time>
    </ksState>
    <ksState>
      <x>-25.365640991345302</x>
      <y>-1.6611205455865694</y>
      <orientation>0.0048</orientation>
      <velocity>2.0</velocity>
      <steeringAngle>0.0</steeringAngle>
      <time>148</time>
    </ksState>
    <ksState>
      <x>-25.165643295340878</x>
      <y>-1.660160549272965</y>
      <orientation>0.0048</orientation>
      <velocity>2.0</velocity>
      <steeringAngle>0.0</steeringAngle>
      <time>149</time>
    </ksState>
    <ksState>
      <x>-24.965645599336455</x>
      <y>-1.6592005529593608</y>
      <orientation>0.0048</orientation>
      <velocity>2.0</velocity>
      <steeringAngle>0.0</steeringAngle>
      <time>150</time>
    </ksState>
    <ksState>
      <x>-24.76564790333203</x>
      <y>-1.6582405566457565</y>
      <orientation>0.0048</orientation>
      <velocity>2.0</velocity>
      <steeringAngle>0.0</steeringAngle>
      <time>151</time>
    </ksState>
    <ksState>
      <x>-24.565650207327607</x>
      <y>-1.6572805603321523</y>
      <orientation>0.0048</orientation>
      <velocity>2.0</velocity>
      <steeringAngle>0.0</steeringAngle>
      <time>152</time>
    </ksState>
    <ksState>
      <x>-24.365652511323184</x>
      <y>-1.656320564018548</y>
      <orientation>0.0048</orientation>
      <velocity>2.0</velocity>
      <steeringAngle>0.0</steeringAngle>
      <time>153</time>
    </ksState>
    <ksState>
      <x>-24.16565481531876</x>
      <y>-1.6553605677049437</y>
      <orientation>0.0048</orientation>
      <velocity>2.0</velocity>
      <steeringAngle>0.0</steeringAngle>
      <time>154</time>
    </ksState>
    <ksState>
      <x>-23.965657119314336</x>
      <y>-1.6544005713913394</y>
      <orientation>0.0048</orientation>
      <velocity>2.0</velocity>
      <steeringAngle>0.0</steeringAngle>
      <time>155</time>
    </ksState>
    <ksState>
      <x>-23.7606594809098</x>
      <y>-1.653416575169895</y>
      <orientation>0.0048</orientation>
      <velocity>2.2</velocity>
      <steeringAngle>0.0</steeringAngle>
      <time>156</time>
    </ksState>
    <ksState>
      <x>-23.535662072904824</x>
      <y>-1.6523365793170903</y>
      <orientation>0.0048</orientation>
      <velocity>2.4000000000000004</velocity>
      <steeringAngle>0.0</steeringAngle>
      <time>157</time>
    </ksState>
    <ksState>
      <x>-23.290664895299408</x>
      <y>-1.651160583832925</y>
      <orientation>0.0048</orientation>
      <velocity>2.6000000000000005</velocity>
      <steeringAngle>0.0</steeringAngle>
      <time>158</time>
    </ksState>
    <ksState>
      <x>-23.025667948093545</x>
      <y>-1.6498885887173995</y>
      <orientation>0.0048</orientation>
      <velocity>2.8000000000000007</velocity>
      <steeringAngle>0.0</steeringAngle>
      <time>159</time>
    </ksState>
    <ksState>
      <x>-22.74067123128724</x>
      <y>-1.6485205939705134</y>
      <orientation>0.0048</orientation>
      <velocity>3.000000000000001</velocity>
      <steeringAngle>0.0</steeringAngle>
      <time>160</time>
    </ksState>
  </ksTrajectory>
</CommonRoadSolution>
